softwrdwrangler/__init__.py
softwrdwrangler/s3/__csv_operation.py
softwrdwrangler/s3/__file_common_operations.py
softwrdwrangler/s3/__geojson_operation.py
softwrdwrangler/s3/__init__.py
softwrdwrangler/s3/__json_operation.py
softwrdwrangler/s3/__pickle_operation.py
softwrdwrangler/s3/__utils.py
softwrdwrangler/secretsmanager/__init__.py
softwrdwrangler/secretsmanager/__secrets.py
softwrdwrangler-0.1.3.dist-info/METADATA
softwrdwrangler-0.1.3.dist-info/WHEEL
softwrdwrangler-0.1.3.dist-info/top_level.txt
softwrdwrangler-0.1.3.dist-info/RECORD
