Metadata-Version: 2.1
Name: softwrdwrangler
Version: 0.1.3
Summary: A package that provides utilities for data wrangling with AWS S3, pandas, and geojson.
Home-page: https://github.com/softwrdai/softwrdwrangler
Author: Md Robiuddin
Author-email: mrrobi040@gmail.com
Keywords: aws,s3,pandas,geojson,pickle,data wrangling,secrets manager
Classifier: Programming Language :: Python :: 3
Classifier: License :: OSI Approved :: Apache Software License
Classifier: Operating System :: Microsoft :: Windows
Requires-Python: >=3.9
Requires-Dist: boto3
Requires-Dist: pandas
Requires-Dist: geojson
